pypi_simple/__init__.py
pypi_simple/classes.py
pypi_simple/client.py
pypi_simple/enums.py
pypi_simple/errors.py
pypi_simple/filenames.py
pypi_simple/html.py
pypi_simple/html_stream.py
pypi_simple/pep691.py
pypi_simple/progress.py
pypi_simple/py.typed
pypi_simple/util.py
pypi_simple-1.7.0.dist-info/METADATA
pypi_simple-1.7.0.dist-info/WHEEL
pypi_simple-1.7.0.dist-info/licenses/LICENSE
pypi_simple-1.7.0.dist-info/RECORD
