Metadata-Version: 2.4
Name: pypi-simple
Version: 1.7.0
Summary: PyPI Simple Repository API client library
Project-URL: Source Code, https://github.com/jwodder/pypi-simple
Project-URL: Bug Tracker, https://github.com/jwodder/pypi-simple/issues
Author-email: John Thorvald Wodder II <pypi-simple@varonathe.org>
License-Expression: MIT
License-File: LICENSE
Keywords: packages,pep503,pip,pypi,simple repository api
Classifier: Development Status :: 5 - Production/Stable
Classifier: Programming Language :: Python :: 3
Classifier: Programming Language :: Python :: 3 :: Only
Classifier: Programming Language :: Python :: 3.8
Classifier: Programming Language :: Python :: 3.9
Classifier: Programming Language :: Python :: 3.10
Classifier: Programming Language :: Python :: 3.11
Classifier: Programming Language :: Python :: 3.12
Classifier: Programming Language :: Python :: 3.13
Classifier: Programming Language :: Python :: Implementation :: CPython
Classifier: Programming Language :: Python :: Implementation :: PyPy
Classifier: Topic :: Software Development :: Libraries :: Python Modules
Classifier: Topic :: System :: Software Distribution
Classifier: Topic :: Text Processing :: Markup :: HTML
Classifier: Typing :: Typed
Requires-Python: >=3.8
Requires-Dist: beautifulsoup4~=4.5
Requires-Dist: mailbits~=0.2
Requires-Dist: packaging>=20
Requires-Dist: pydantic~=2.0
Requires-Dist: requests~=2.20
Provides-Extra: tqdm
Requires-Dist: tqdm; extra == 'tqdm'
